{
  "template": {
    "data": {
      "type": "gas_object",
      "attributes": {
        "name": "Объект 654057",
        "description": "Объект из pto_obj_adr. ID: 654057",
        "status": "active",
        "custom_data": {
          "source_database": "dog",
          "source_table": "pto_obj_adr",
          "source_id": 654057,
          "p2": 18,
          "p3": 1477,
          "street": 3789,
          "dom": 78,
          "korpus": 0
        }
      },
      "relationships": {
        "address": {
          "data": {
            "type": "address",
            "attributes": {
              "country": "Россия",
              "region": "Нижегородская область",
              "city": "Вадский",
              "settlement": "Зеленые Горы",
              "area": "Нижегородская область район",
              "zip_code": "606380",
              "street": "ул. Садовая",
              "house": "78",
              "block": null,
              "flat": 123,
              "room": 3,
              "region_fias_id": "region_52",
              "city_fias_id": "F094D1FD-709B-4D74-8AD9-3BD85C05AE6F",
              "settlement_fias_id": "786AF4A2-BB49-4EEA-9CBF-15C6E60EA3F1",
              "area_fias_id": "F094D1FD-709B-4D74-8AD9-3BD85C05AE6F",
              "house_fias_id": "F094D1FD-709B-4D74-8AD9-3BD85C05AE6F",
              "street_fias_id": null,
              "extra": "Original: p2=18, p3=1477, street=3789",
              "oktmo": 123456789,
              "cadastral_number": "123421W",
              "cadastral_home_number": "123421H",
              "okato": "123421H",
              "title": "Нижегородская область, ул Садовая 78",
              "has_capital_construction": true,
              "room_type": "apartment_building"
            }
          }
        }
      }
    }
  },
  "metadata": {
    "source": "pto_obj_adr",
    "source_id": 654057,
    "template_number": 286405,
    "created_at": "2025-10-01T08:12:35.608624"
  }
}