{
  "template": {
    "data": {
      "type": "gas_object",
      "attributes": {
        "name": "Объект 537916",
        "description": "Объект из pto_obj_adr. ID: 537916",
        "status": "active",
        "custom_data": {
          "source_database": "dog",
          "source_table": "pto_obj_adr",
          "source_id": 537916,
          "p2": 84,
          "p3": 0,
          "street": 9841,
          "dom": 11,
          "korpus": 0
        }
      },
      "relationships": {
        "address": {
          "data": {
            "type": "address",
            "attributes": {
              "country": "Россия",
              "region": "Нижегородская область",
              "city": "Сосновское",
              "settlement": "Сосновское",
              "area": "Нижегородская область район",
              "zip_code": "606170",
              "street": "ул. Больничная",
              "house": "11",
              "block": null,
              "flat": 123,
              "room": 3,
              "region_fias_id": "region_52",
              "city_fias_id": "33A8D0AF-67C7-4BA3-BA18-249B316B67F2",
              "settlement_fias_id": "33A8D0AF-67C7-4BA3-BA18-249B316B67F2",
              "area_fias_id": "33A8D0AF-67C7-4BA3-BA18-249B316B67F2",
              "house_fias_id": "33A8D0AF-67C7-4BA3-BA18-249B316B67F2",
              "street_fias_id": null,
              "extra": "Original: p2=84, p3=0, street=9841",
              "oktmo": 123456789,
              "cadastral_number": "123421W",
              "cadastral_home_number": "123421H",
              "okato": "123421H",
              "title": "Нижегородская область, ул Больничная 11",
              "has_capital_construction": true,
              "room_type": "apartment_building"
            }
          }
        }
      }
    }
  },
  "metadata": {
    "source": "pto_obj_adr",
    "source_id": 537916,
    "created_at": "2025-10-01T08:38:38.204246",
    "batch_processed": false
  }
}