{
  "template": {
    "data": {
      "type": "gas_object",
      "attributes": {
        "name": "Объект 596790"
      },
      "relationships": {
        "address": {
          "data": {
            "type": "address",
            "attributes": {
              "country": "Россия",
              "region": "Нижегородская область",
              "city": "Сокольский",
              "settlement": "Хмельничное",
              "area": "Нижегородская область район",
              "zip_code": 606670,
              "street": "ул. Придорожная",
              "house": 3,
              "block": null,
              "flat": 123,
              "room": 3,
              "region_fias_id": "region_52",
              "city_fias_id": "A50632F1-48A4-401C-8B4C-03128AA29D97",
              "settlement_fias_id": "05DD36E8-EF5C-4FAD-9536-DD18675ACDD2",
              "area_fias_id": "A50632F1-48A4-401C-8B4C-03128AA29D97",
              "house_fias_id": "A50632F1-48A4-401C-8B4C-03128AA29D97",
              "street_fias_id": null,
              "extra": "Original: p2=81, p3=4821, street=18023",
              "oktmo": 123456789,
              "cadastral_number": "123421W",
              "cadastral_home_number": "123421H",
              "okato": "123421H",
              "title": "Нижегородская область, ул. Придорожная 3",
              "has_capital_construction": true,
              "room_type": "apartment_building"
            }
          }
        }
      }
    }
  },
  "metadata": {
    "source": "pto_obj_adr",
    "source_id": 596790,
    "created_at": "2025-10-10T09:06:25.283136",
    "batch_processed": false
  },
  "api_data": {
    "data": {
      "type": "gas_object",
      "attributes": {
        "name": "Объект 596790"
      },
      "relationships": {
        "address": {
          "data": {
            "type": "address",
            "attributes": {
              "country": "Россия",
              "region": "Нижегородская область",
              "city": "Сокольский",
              "settlement": "Хмельничное",
              "area": "Нижегородская область район",
              "zip_code": 606670,
              "street": "ул. Придорожная",
              "house": 3,
              "block": null,
              "flat": 123,
              "room": 3,
              "region_fias_id": "region_52",
              "city_fias_id": "A50632F1-48A4-401C-8B4C-03128AA29D97",
              "settlement_fias_id": "05DD36E8-EF5C-4FAD-9536-DD18675ACDD2",
              "area_fias_id": "A50632F1-48A4-401C-8B4C-03128AA29D97",
              "house_fias_id": "A50632F1-48A4-401C-8B4C-03128AA29D97",
              "street_fias_id": null,
              "extra": "Original: p2=81, p3=4821, street=18023",
              "oktmo": 123456789,
              "cadastral_number": "123421W",
              "cadastral_home_number": "123421H",
              "okato": "123421H",
              "title": "Нижегородская область, ул. Придорожная 3",
              "has_capital_construction": true,
              "room_type": "apartment_building"
            }
          }
        }
      }
    }
  }
}